maru/.DS_Store
maru/__init__.py
maru/analyzer.py
maru/factory/__init__.py
maru/factory/analyzer.py
maru/factory/lemmatizer.py
maru/factory/tagger.py
maru/feature/__init__.py
maru/feature/extractor/__init__.py
maru/feature/extractor/abstract.py
maru/feature/extractor/cache.py
maru/feature/extractor/pipeline.py
maru/feature/extractor/pymorphy.py
maru/feature/extractor/stem.py
maru/feature/extractor/suffix.py
maru/feature/extractor/word.py
maru/feature/vocabulary.py
maru/feature/window.py
maru/grammeme/__init__.py
maru/grammeme/abstract.py
maru/grammeme/animacy.py
maru/grammeme/aspect.py
maru/grammeme/case.py
maru/grammeme/degree.py
maru/grammeme/gender.py
maru/grammeme/mood.py
maru/grammeme/number.py
maru/grammeme/numform.py
maru/grammeme/person.py
maru/grammeme/pos.py
maru/grammeme/tense.py
maru/grammeme/variant.py
maru/grammeme/verbform.py
maru/grammeme/voice.py
maru/lemmatizer/__init__.py
maru/lemmatizer/abstract.py
maru/lemmatizer/cache.py
maru/lemmatizer/dummy.py
maru/lemmatizer/pymorphy.py
maru/morph.py
maru/pymorphy/__init__.py
maru/pymorphy/analyzer.py
maru/pymorphy/grammeme/__init__.py
maru/pymorphy/grammeme/animacy.py
maru/pymorphy/grammeme/aspect.py
maru/pymorphy/grammeme/case.py
maru/pymorphy/grammeme/degree.py
maru/pymorphy/grammeme/gender.py
maru/pymorphy/grammeme/mood.py
maru/pymorphy/grammeme/number.py
maru/pymorphy/grammeme/person.py
maru/pymorphy/grammeme/pos.py
maru/pymorphy/grammeme/tense.py
maru/pymorphy/grammeme/verbform.py
maru/pymorphy/grammeme/voice.py
maru/pymorphy/tag.py
maru/resource/.DS_Store
maru/resource/__init__.py
maru/resource/crf/__init__.py
maru/resource/crf/extractor.joblib
maru/resource/crf/tagger.crfsuite
maru/resource/crf/tags.joblib
maru/resource/linear/.DS_Store
maru/resource/linear/__init__.py
maru/resource/linear/coefficients.gz
maru/resource/linear/extractor.joblib
maru/resource/linear/intercept.gz
maru/resource/linear/tags.joblib
maru/resource/linear/vocabulary.json
maru/resource/rnn/__init__.py
maru-0.2.0.dist-info/LICENSE
maru-0.2.0.dist-info/WHEEL
maru-0.2.0.dist-info/METADATA
maru-0.2.0.dist-info/RECORD
