Metadata-Version: 2.1
Name: maru
Version: 0.2.0
Summary: Morphological Analyzer for Russian 💬
Home-page: https://github.com/chomechome/maru
License: MIT
Author: Vladislav Blinov
Author-email: cunningplan@yandex.ru
Requires-Python: >=3.6,<4.0
Classifier: License :: OSI Approved :: MIT License
Classifier: Programming Language :: Python :: 3
Classifier: Programming Language :: Python :: 3.6
Classifier: Programming Language :: Python :: 3.7
Classifier: Programming Language :: Python :: 3.8
Classifier: Programming Language :: Python :: Implementation :: CPython
Provides-Extra: gpu
Provides-Extra: tf
Requires-Dist: joblib (>=0.11.0)
Requires-Dist: keras (>=2.2.2)
Requires-Dist: lru-dict (>=1.1.6)
Requires-Dist: numpy (>=1.15.0)
Requires-Dist: pymorphy2[fast] (>=0.8)
Requires-Dist: python-crfsuite (>=0.9.5)
Requires-Dist: scipy (>=1.1.0)
Requires-Dist: tensorflow (>=1.14.0); extra == "tf"
Requires-Dist: tensorflow-gpu (>=1.14.0); extra == "gpu"
Project-URL: Repository, https://github.com/chomechome/maru
